{
  "_comment": "Static work assignments per machine hostname. Run `hostname` to get your machine's id.",
  "census": "m003-m412",
  "_timing_notes": {
    "qq50_ell2_per_slope_M4": "~19s (12 workers)",
    "qq50_ell3_per_slope_M4": "~96s (12 workers)",
    "qq50_ell2_per_slope_M1": "~25s (8 workers)",
    "qq50_ell3_per_slope_M1": "~144s (8 workers)",
    "split_rationale": "M4 takes Q=2..7 (50 slopes, ~49 min), M1 takes Q=8..10 (32 slopes, ~45 min). Both finish in ~49 min."
  },
  "machines": {
    "Soochangs-MacBook-Pro.local": {
      "name": "M4 Max (12 workers)",
      "tasks": [
        {"type": "kernels", "qq": 50, "q_min": 2, "q_max": 7, "p_min": -10, "p_max": 10, "workers": 12,
         "_note": "74 slopes: Q=2..7, |P|≤10 — 54 ℓ=2 + 20 ℓ=3 x96s each. ETA ~49 min."},
        {"type": "iref",    "qq": 25,
         "_note": "Run after qq=50 kernels are done and merged."},
        {"type": "iref",    "qq": 50},
        {"type": "nc",      "qq": 20}
      ]
    },
    "SNU-CTPs-MacBook-Pro.local": {
      "name": "M1 Mac (8 workers)",
      "_setup": "brew install python@3.12 && cd v0.4 && python3.12 -m pip install -e . && ./run.sh",
      "tasks": [
        {"type": "kernels", "qq": 50, "q_min": 8, "q_max": 10, "p_min": -10, "p_max": 10, "workers": 8,
         "_note": "32 slopes: Q=8..10, |P|≤10 — 16 ℓ=2 + 16 ℓ=3 x144s each. ETA ~45 min."}
      ]
    }
  }
}
